{
  "transferencias": [
    {
      "id": "1",
      "valor": 35,
      "destino": "1212-1",
      "data": "2020-11-04T16:30:10.710Z"
    },
    {
      "id": "2",
      "valor": 40,
      "destino": "1213-1",
      "data": "2020-11-04T21:24:10.710Z"
    },
    {
      "id": "3",
      "valor": 12.5,
      "destino": "1214-1",
      "data": "2020-11-05T21:14:10.710Z"
    },
    {
      "valor": 12321,
      "destino": "dads",
      "data": "2022-02-10T23:59:24.652Z",
      "id": "CUQ0X59"
    },
    {
      "valor": 5555,
      "destino": "ccccc",
      "data": "2022-02-11T00:00:17.337Z",
      "id": "2eEnZZK"
    },
    {
      "valor": 7777,
      "destino": "dasdd",
      "data": "2022-02-11T00:20:52.996Z",
      "id": "MVdreFA"
    }
  ]
}